README.rst
setup.py
astmonkey/__init__.py
astmonkey/transformers.py
astmonkey/utils.py
astmonkey/visitors.py
astmonkey.egg-info/PKG-INFO
astmonkey.egg-info/SOURCES.txt
astmonkey.egg-info/dependency_links.txt
astmonkey.egg-info/requires.txt
astmonkey.egg-info/top_level.txt