Metadata-Version: 1.1
Name: astmonkey
Version: 0.1.1
Summary: astmonkey is a set of tools to play with Python AST.
Home-page: https://github.com/konradhalas/astmonkey
Author: Konrad Hałas
Author-email: halas.konrad@gmail.com
License: UNKNOWN
Platform: UNKNOWN
Classifier: Intended Audience :: Developers
Classifier: Programming Language :: Python :: 2.6
Classifier: Programming Language :: Python :: 2.7
Classifier: Programming Language :: Python :: 3.1
Classifier: Programming Language :: Python :: 3.2
Classifier: Programming Language :: Python :: 3.3
Classifier: License :: OSI Approved :: Apache Software License
